jibberjabber/__init__.py
jibberjabber/dictonaries.py
jibberjabber/dist.products
jibberjabber/dist.words
jibberjabber/generators.py
jibber_jabber-0.0.9.dist-info/LICENSE
jibber_jabber-0.0.9.dist-info/METADATA
jibber_jabber-0.0.9.dist-info/WHEEL
jibber_jabber-0.0.9.dist-info/top_level.txt
jibber_jabber-0.0.9.dist-info/RECORD
