Metadata-Version: 2.1
Name: jibber-jabber
Version: 0.0.9
Summary: Simple product name generator
Home-page: https://github.com/cerodriguez/gibberish
Author: CE
Author-email: celupo@pm.me
License: UNKNOWN
Platform: UNKNOWN
Classifier: Programming Language :: Python :: 3
Classifier: License :: OSI Approved :: GNU General Public License v3 or later (GPLv3+)
Classifier: Operating System :: OS Independent
Requires-Python: >=3.6
